bellow/__init__.py
bellow/__version__.py
bellow/device_metadata.py
bellow/main.py
bellow/soundeffects.py
bellow/audio/__init__.py
bellow/audio/dump.ogg
bellow/audio/micoff.ogg
bellow/audio/micon.ogg
bellow-1.0.0.dist-info/LICENSE.txt
bellow-1.0.0.dist-info/METADATA
bellow-1.0.0.dist-info/WHEEL
bellow-1.0.0.dist-info/entry_points.txt
bellow-1.0.0.dist-info/top_level.txt
bellow-1.0.0.dist-info/RECORD
