Metadata-Version: 2.1
Name: bellow
Version: 1.0.0
Summary: Implements a pushbutton interface to the Whisper transformer using a global hotkey
Home-page: https://github.com/djparente/bellow
Author: Daniel J. Parente
Author-email: dan.parente@gmail.com
Classifier: Programming Language :: Python :: 3
Classifier: License :: OSI Approved :: MIT License
Classifier: Operating System :: OS Independent
Requires-Python: >=3.7
License-File: LICENSE.txt
Requires-Dist: clipboard (>=0.0.4)
Requires-Dist: keyboard (>=0.13.5)
Requires-Dist: numpy (>=1.24.1)
Requires-Dist: sounddevice (>=0.4.6)
Requires-Dist: soundfile (>=0.12.1)
Requires-Dist: transformers (>=4.33.2)
